plotano/__init__.py
plotano/application.py
plotano/cambio.py
plotano/component/__init__.py
plotano/component/base.py
plotano/component/chatbot_database_factory.py
plotano/component/constants.py
plotano/database_ranking_test.ipynb
plotano/database_test.ipynb
plotano/db/__init__.py
plotano/db/qa_database.py
plotano/db/ranking_database.py
plotano/frontend/.gitignore
plotano/frontend/README.md
plotano/frontend/dist/assets/index-6be01a5f.css
plotano/frontend/dist/assets/index-f770d60f.js
plotano/frontend/dist/index.html
plotano/frontend/dist/vite.svg
plotano/frontend/index.html
plotano/frontend/jsconfig.json
plotano/frontend/package.json
plotano/frontend/public/vite.svg
plotano/frontend/src/App.svelte
plotano/frontend/src/Chat.svelte
plotano/frontend/src/Chatbot.svelte
plotano/frontend/src/Dropdown.svelte
plotano/frontend/src/Feedback.svelte
plotano/frontend/src/RankedChatbot.svelte
plotano/frontend/src/app.css
plotano/frontend/src/assets/svelte.svg
plotano/frontend/src/lib/Annotations/QuestionRating.svelte
plotano/frontend/src/lib/DashboardFeedback/ColumnChart.svelte
plotano/frontend/src/lib/DashboardFeedback/HistogramAnswer.svelte
plotano/frontend/src/lib/DashboardFeedback/HistogramQuestion.svelte
plotano/frontend/src/lib/DashboardFeedback/HorizontalStackedBar.svelte
plotano/frontend/src/lib/DashboardFeedback/MetricCardAbsolute.svelte
plotano/frontend/src/lib/DashboardFeedback/MetricCardPercentage.svelte
plotano/frontend/src/lib/DashboardFeedback/QACard.svelte
plotano/frontend/src/lib/DashboardFeedback/QATable.svelte
plotano/frontend/src/main.js
plotano/frontend/src/normalize.css
plotano/frontend/src/store.js
plotano/frontend/src/styles.css
plotano/frontend/src/utils.js
plotano/frontend/src/vite-env.d.ts
plotano/frontend/svelte.config.js
plotano/frontend/vite.config.js
plotano/llm/__init__.py
plotano/llm/abs_llm.py
plotano/llm/constants.py
plotano/llm/huggingface.py
plotano/llm/model_factory.py
plotano/llm/openai.py
plotano/rlhf/__init__.py
plotano/rlhf/rlhf.py
plotano-0.0.0.dist-info/LICENSE.txt
plotano-0.0.0.dist-info/METADATA
plotano-0.0.0.dist-info/WHEEL
plotano-0.0.0.dist-info/RECORD
